single_cycle/rv_defs.v
//opcodes for decoder
`define opcode_R    7'b0110011
`define opcode_Ia   7'b0010011
`define opcode_Ib   7'b0000011
`define opcode_S    7'b0100011
`define opcode_B    7'b1100011
`define opcode_Ul   7'b0110111
`define opcode_Ui   7'b0010111
`define opcode_J    7'b1101111
`define opcode_Ij   7'b1100111
`define opcode_Ec   7'b1110011
`define opcode_Eb   7'b0110011

// for rv_alu
`define ALU_ADD      4'b0000     //  rd = rs1 + rs2;        add
`define ALU_SUB      4'b0001     //  rd = rs1 - rs2;        sub //set zero output
`define ALU_XOR      4'b0010     //  rd = rs1 ^ rs2;        exclusively or
`define ALU_OR       4'b0011     //  rd = rs1 | rs2;        or
`define ALU_AND      4'b0100     //  rd = rs1 & rs2;        and
`define ALU_SLL      4'b0101     //  rd = rs1 <<< rs2;      shift left logical
`define ALU_SRL      4'b0110     //  rd = rs1 >>> rs2;      shift right logical     (1011 >> 1 == 0101)
`define ALU_SRA      4'b0111     //  rd = rs1 >> rs2;       shift right ariphmetic  (1011 >> 1 == 1101)

`define ALU_SLT      4'b1000     //  rd = rs1 < rs2;        set rd=1 if less than           (0xFF<0 true) 
`define ALU_SLTU     4'b1001     //  rd = rs1 < rs2;        set rd=1 if less than unsigned  (0xFF<0 false)

// alu_rs2 multiplexer
`define ALU_MUX_REG_REG 1'b0
`define ALU_MUX_REG_IMM 1'b1

// result multiplexer
`define RES_MPX_ALU 2'b00
`define RES_MPX_MEM 2'b01
`define RES_MPX_PC4 2'b10

// load module
`define LOAD_B      3'b000
`define LOAD_HW     3'b001
`define LOAD_W      3'b010
`define LOAD_BU     4'b011
`define LOAD_HWU    3'b100

single_cycle/load_module/load_module.v
//! * module thats allow to load from memory single byte and half byte to register
`include "../rv_defs.v"
module load_module(
    input [2:0] load_enable,
    input [1:0] low_address, // check what number of byte is wanted to load (low two bits of memory address)
    input [31:0] in,
    output reg [31:0] out
);

always @* begin
    case(load_enable)
        `LOAD_B: begin
            case(low_address)
                2'b00: out = {{24{in[7]}}, in[7:0]};
                2'b01: out = {{24{in[15]}}, in[15:8]};
                2'b10: out = {{24{in[23]}}, in[23:16]};
                2'b11: out = {{24{in[31]}}, in[31:24]};
            endcase
        end
        
        `LOAD_HW: begin
            case(low_address)
                2'b00: out = {{16{in[15]}}, in[15:0]};
               // begin
               //     out[15:0] = in[15:0];
               //     if(in[15])  out[31:16] = 1;
               //     else        out[31:16] = 0;
               // end
                2'b01: out = {{16{in[23]}}, in[23:8]};
                2'b10: out = {{16{in[31]}},in[31:16]};
                default: out = 32'bx;
            endcase
        end
        
        `LOAD_W: out = in;
        
        `LOAD_BU: begin
            case(low_address)
                2'b00: out = {{24{1'b0}}, in[7:0]};
                2'b01: out = {{24{1'b0}}, in[15:8]};
                2'b10: out = {{24{1'b0}}, in[23:16]};
                2'b11: out = {{24{1'b0}}, in[31:24]};
            endcase
        end
        
        `LOAD_HWU: begin
            case(low_address)
                2'b00: out = {{16{1'b0}}, in[15:0]};
                2'b01: out = {{16{1'b0}}, in[23:8]};
                2'b10: out = {{16{1'b0}}, in[31:16]};
                default: out = 32'bx;
            endcase
        end

    endcase
end

endmodule

single_cycle/load_module/test_load_module.v
`timescale 1ns/100ps

module test_load_module();

reg [31:0]in;
reg [2:0] load;
reg [1:0] low_address;

load_module load1 (.load_enable(load), .low_address(low_address), .in(in));

initial begin
    $dumpvars;
    $display("start");
    #20 $finish();
end

initial begin
    in = 32'hf2f4f6f8;
    #0;

    low_address = 0;
    load = 0;
    #1;
    low_address = 1;
    load = 0;
    #1;
    low_address = 2;
    load = 0;
    #1;
    low_address = 3;
    load = 0;

    #2;low_address = 0;
    load = 1;
    #1;
    low_address = 1;
    load = 1;
    #1;
    low_address = 2;
    load = 1;
    #1;
    low_address = 3;
    load = 1;
    #2;
    
    
    low_address = 0;
    load = 3;
    #1;
    low_address = 1;
    load = 3;
    #1;
    low_address = 2;
    load = 3;
    #1;
    low_address = 3;
    load = 3;
    #2;

    low_address = 0;
    load = 4;
    #1;
    low_address = 1;
    load = 4;
    #1;
    low_address = 2;
    load = 4;
    #1;
    low_address = 3;
    load = 4;
    #2;

end

endmodule

single_cycle/load_module/dump.vcd
$date
	Mon May 30 16:22:11 2022
$end
$version
	Icarus Verilog
$end
$timescale
	100ps
$end
$scope module test_load_module $end
$var reg 32 ! in [31:0] $end
$var reg 3 " load [2:0] $end
$var reg 2 # low_address [1:0] $end
$scope module load1 $end
$var wire 32 $ in [31:0] $end
$var wire 3 % load_enable [2:0] $end
$var wire 2 & low_address [1:0] $end
$var reg 32 ' out [31:0] $end
$upscope $end
$upscope $end
$enddefinitions $end
#0
$dumpvars
b11111111111111111111111111111000 '
b0 &
b0 %
b11110010111101001111011011111000 $
b0 #
b0 "
b11110010111101001111011011111000 !
$end
#10
b11111111111111111111111111110110 '
b1 #
b1 &
#20
b11111111111111111111111111110100 '
b10 #
b10 &
#30
b11111111111111111111111111110010 '
b11 #
b11 &
#50
b11111111111111111111011011111000 '
b1 "
b1 %
b0 #
b0 &
#60
b11111111111111111111010011110110 '
b1 #
b1 &
#70
b11111111111111111111001011110100 '
b10 #
b10 &
#80
bx '
b11 #
b11 &
#100
b11111000 '
b11 "
b11 %
b0 #
b0 &
#110
b11110110 '
b1 #
b1 &
#120
b11110100 '
b10 #
b10 &
#130
b11110010 '
b11 #
b11 &
#150
b1111011011111000 '
b100 "
b100 %
b0 #
b0 &
#160
b1111010011110110 '
b1 #
b1 &
#170
b1111001011110100 '
b10 #
b10 &
#180
bx '
b11 #
b11 &
